momento_wire_types/__init__.py
momento_wire_types/py.typed
momento_wire_types/v319/__init__.py
momento_wire_types/v319/auth_pb2.py
momento_wire_types/v319/auth_pb2.pyi
momento_wire_types/v319/auth_pb2_grpc.py
momento_wire_types/v319/cacheclient_pb2.py
momento_wire_types/v319/cacheclient_pb2.pyi
momento_wire_types/v319/cacheclient_pb2_grpc.py
momento_wire_types/v319/cachepubsub_pb2.py
momento_wire_types/v319/cachepubsub_pb2.pyi
momento_wire_types/v319/cachepubsub_pb2_grpc.py
momento_wire_types/v319/common_pb2.py
momento_wire_types/v319/common_pb2.pyi
momento_wire_types/v319/common_pb2_grpc.py
momento_wire_types/v319/controlclient_pb2.py
momento_wire_types/v319/controlclient_pb2.pyi
momento_wire_types/v319/controlclient_pb2_grpc.py
momento_wire_types/v319/extensions_pb2.py
momento_wire_types/v319/extensions_pb2.pyi
momento_wire_types/v319/extensions_pb2_grpc.py
momento_wire_types/v319/permissionmessages_pb2.py
momento_wire_types/v319/permissionmessages_pb2.pyi
momento_wire_types/v319/permissionmessages_pb2_grpc.py
momento_wire_types/v319/token_pb2.py
momento_wire_types/v319/token_pb2.pyi
momento_wire_types/v319/token_pb2_grpc.py
momento_wire_types/v4/__init__.py
momento_wire_types/v4/auth_pb2.py
momento_wire_types/v4/auth_pb2.pyi
momento_wire_types/v4/auth_pb2_grpc.py
momento_wire_types/v4/cacheclient_pb2.py
momento_wire_types/v4/cacheclient_pb2.pyi
momento_wire_types/v4/cacheclient_pb2_grpc.py
momento_wire_types/v4/cachepubsub_pb2.py
momento_wire_types/v4/cachepubsub_pb2.pyi
momento_wire_types/v4/cachepubsub_pb2_grpc.py
momento_wire_types/v4/common_pb2.py
momento_wire_types/v4/common_pb2.pyi
momento_wire_types/v4/common_pb2_grpc.py
momento_wire_types/v4/controlclient_pb2.py
momento_wire_types/v4/controlclient_pb2.pyi
momento_wire_types/v4/controlclient_pb2_grpc.py
momento_wire_types/v4/extensions_pb2.py
momento_wire_types/v4/extensions_pb2.pyi
momento_wire_types/v4/extensions_pb2_grpc.py
momento_wire_types/v4/permissionmessages_pb2.py
momento_wire_types-0.127.4.dist-info/METADATA
momento_wire_types-0.127.4.dist-info/WHEEL
momento_wire_types-0.127.4.dist-info/RECORD
