Metadata-Version: 2.1
Name: momento-wire-types
Version: 0.127.4
Summary: Momento Client Proto Generated Files
Home-page: https://gomomento.com
License: Apache-2.0
Keywords: Momento,caching,key-value store,serverless
Author: Momento
Author-email: hello@momentohq.com
Requires-Python: >=3.7,<4.0
Classifier: Development Status :: 5 - Production/Stable
Classifier: Environment :: Console
Classifier: Framework :: AsyncIO
Classifier: Intended Audience :: Developers
Classifier: License :: OSI Approved :: Apache Software License
Classifier: Natural Language :: English
Classifier: Operating System :: OS Independent
Classifier: Programming Language :: Python :: 3
Classifier: Programming Language :: Python :: 3.7
Classifier: Programming Language :: Python :: 3.8
Classifier: Programming Language :: Python :: 3.9
Classifier: Programming Language :: Python :: 3.10
Classifier: Programming Language :: Python :: 3.11
Classifier: Topic :: Internet
Classifier: Typing :: Typed
Requires-Dist: grpcio
Requires-Dist: protobuf (>=3,<5)
Project-URL: Documentation, https://docs.momentohq.com/
Project-URL: Repository, https://github.com/momentohq/client-protos
